__init__.py
dataspec.py
io01a_import_from_dropbox.py
io01b_import_local.py
io02_push_to_db.py
io03_push_to_gsheets.py
io04_copy_to_dir.py
io05_push_to_git.py
p01_parse_files.py
p02_combine_files.py
p03_create_grids.py
pipeline_util.py
run_pipeline.py
server.py
threadsheets.py
threadsheets/__init__.py
threadsheets/dataspec.py
threadsheets/io01a_import_from_dropbox.py
threadsheets/io01b_import_local.py
threadsheets/io02_push_to_db.py
threadsheets/io03_push_to_gsheets.py
threadsheets/io04_copy_to_dir.py
threadsheets/io05_push_to_git.py
threadsheets/p01_parse_files.py
threadsheets/p02_combine_files.py
threadsheets/p03_create_grids.py
threadsheets/pipeline_util.py
threadsheets/run_pipeline.py
threadsheets/server.py
threadsheets/threadsheets.py
threadsheets-1.0.6.dist-info/LICENSE
threadsheets-1.0.6.dist-info/METADATA
threadsheets-1.0.6.dist-info/WHEEL
threadsheets-1.0.6.dist-info/top_level.txt
threadsheets-1.0.6.dist-info/RECORD
