Metadata-Version: 2.1
Name: threadsheets
Version: 1.0.6
Summary: Weave Tabular Datasets into Graphical Models
Author-email: Jeff Jacobs <jpj2122@columbia.edu>
Project-URL: Homepage, https://github.com/jpowerj/threadsheets
Project-URL: Bug Tracker, https://github.com/jpowerj/threadsheets/issues
Classifier: Programming Language :: Python :: 3
Classifier: License :: OSI Approved :: MIT License
Classifier: Operating System :: OS Independent
Requires-Python: >=3.7
License-File: LICENSE
Requires-Dist: python-dotenv
Requires-Dist: PyGithub
Requires-Dist: pandas
Requires-Dist: numpy
